visitor_design_pattern/__init__.py
visitor_design_pattern/__version__.py
visitor_design_pattern/visitor_design_pattern.py
visitor_design_pattern-1.0.10.dist-info/licenses/AUTHORS.rst
visitor_design_pattern-1.0.10.dist-info/METADATA
visitor_design_pattern-1.0.10.dist-info/WHEEL
visitor_design_pattern-1.0.10.dist-info/top_level.txt
visitor_design_pattern-1.0.10.dist-info/RECORD
