Metadata-Version: 2.4
Name: visitor_design_pattern
Version: 1.0.10
Summary: Radiative Transfer Model template
Home-page: https://gitlab.rayference.dansaert.be/project-x01/drivers/the_visitors
Author: Nicolas Misk
Author-email: nicolas.misk@rayference.eu
Keywords: visitor_design_pattern
Classifier: Development Status :: 2 - Pre-Alpha
Classifier: Intended Audience :: Developers
Classifier: Natural Language :: English
Classifier: Programming Language :: Python :: 3
Classifier: Programming Language :: Python :: 3.5
Classifier: Programming Language :: Python :: 3.6
Classifier: Programming Language :: Python :: 3.7
Classifier: Programming Language :: Python :: 3.8
Requires-Python: >=3.5
License-File: AUTHORS.rst
Dynamic: author
Dynamic: author-email
Dynamic: classifier
Dynamic: description
Dynamic: home-page
Dynamic: keywords
Dynamic: license-file
Dynamic: requires-python
Dynamic: summary
